nbterm/__init__.py
nbterm/_version.py
nbterm/cell.py
nbterm/format.py
nbterm/help.py
nbterm/key_bindings.py
nbterm/nbterm.py
nbterm/notebook.py
vinbterm-0.1.6.dist-info/LICENSE
vinbterm-0.1.6.dist-info/METADATA
vinbterm-0.1.6.dist-info/WHEEL
vinbterm-0.1.6.dist-info/entry_points.txt
vinbterm-0.1.6.dist-info/top_level.txt
vinbterm-0.1.6.dist-info/RECORD
