Metadata-Version: 2.1
Name: vinbterm
Version: 0.1.6
Summary: A tool for viewing, editing and executing Jupyter Notebooks in the terminal
Home-page: https://github.com/jimbozhang/nbterm
Author: David Brochart, Junbo Zhang
Author-email: dr.jimbozhang@gmail.com
Classifier: Programming Language :: Python :: 3
Classifier: License :: OSI Approved :: MIT License
Classifier: Operating System :: OS Independent
Requires-Python: >=3.7
License-File: LICENSE
Requires-Dist: prompt-toolkit >=3.0.16
Requires-Dist: typer >=0.4.0
Requires-Dist: pygments
Requires-Dist: rich
Requires-Dist: kernel-driver >=0.0.6
Requires-Dist: ipykernel
Provides-Extra: test
Requires-Dist: mypy ; extra == 'test'
Requires-Dist: flake8 ; extra == 'test'
Requires-Dist: black ; extra == 'test'
Requires-Dist: pytest ; extra == 'test'
